<?xml version="1.0" encoding="UTF-8"?>

<mule xmlns:json="http://www.mulesoft.org/schema/mule/json" xmlns:ee="http://www.mulesoft.org/schema/mule/ee/core"
	xmlns="http://www.mulesoft.org/schema/mule/core"
	xmlns:doc="http://www.mulesoft.org/schema/mule/documentation" xmlns:xsi="http://www.w3.org/2001/XMLSchema-instance" xsi:schemaLocation="http://www.mulesoft.org/schema/mule/core http://www.mulesoft.org/schema/mule/core/current/mule.xsd
http://www.mulesoft.org/schema/mule/ee/core http://www.mulesoft.org/schema/mule/ee/core/current/mule-ee.xsd
http://www.mulesoft.org/schema/mule/json http://www.mulesoft.org/schema/mule/json/current/mule-json.xsd">
	<sub-flow name="outbound-poAck-processing-subflow" doc:id="32400225-6332-4357-9d81-41574e4995c7" >
		<logger level="INFO" doc:name="LOG INFO : START" doc:id="d5ab11d1-0528-47bd-9b37-d8e497f329d3" message="#[%dw 2.0&#10;output application/json&#10;---&#10;{&#10;	event: &quot;START&quot;,&#10;	flow: flow.name,&#10;	application: app.name,&#10;	environment: p('mule.env'),&#10;	timestamp: now(),&#10;	correlationId: vars.initialVariables.correlationId,&#10;	sourceSystem: &quot;P21&quot;,&#10;	targetSystem: &quot;APM - Anypoint Partner Manager&quot;&#10;}]" />
		<ee:transform doc:name="var : httpOperation - get Ack Data" doc:id="de81ff63-a1cc-49e3-987e-eedc384445de" >
			<ee:message />
			<ee:variables >
				<ee:set-variable resource="dwl/outbound-poAck-processing-subflow/v_httpOperationGetAckData.dwl" variableName="httpOperation" />
			</ee:variables>
		</ee:transform>
		<flow-ref doc:name="Flow Reference To commom-http-request-subflow" doc:id="924795c2-b69a-42a8-9fc8-15248a4fbe64" name="common-http-request-subflow" target="ackData" />
		<ee:transform doc:name="View to CDM transformation" doc:id="29cb1dbb-24da-4cde-8623-83e17b29ae85" >
			<ee:message >
				<ee:set-payload resource="dwl/outbound-poAck-processing-subflow/p_cdmMapping.dwl" />
			</ee:message>
		</ee:transform>
		<logger level="DEBUG" doc:name="LOG DEBUG:  Parallel for each" doc:id="dd2a3676-5471-4371-89ce-821bd360d8e3" message='#[%dw 2.0&#10;output application/json&#10;---&#10;{&#10;	event: "Parllel for each process started",&#10;	flow: flow.name,&#10;	application: app.name,&#10;	timestamp: now(),&#10;	correlationId: vars.initialVariables.correlationId,&#10;	poMapping: payload&#10;}]' category="${logger.debug.category}" />
		<parallel-foreach doc:name="Parallel For Each : Iteration over POs" doc:id="1263a5ed-f87d-48ad-b325-fcf1416e6412" collection="#[payload]">
			<try doc:name="Try" doc:id="5569346c-9f15-4630-a9ad-1821bc79946e" >
				<json:validate-schema doc:name="Validate schema" doc:id="85253572-4145-44bf-a03b-5978ac0da2d5" schema="schema/POACK_OUTBOUND_JSON_SCHEMA.json" />
				<ee:transform doc:name="var: httpOperation- post APM" doc:id="78e0011f-a283-4ada-a5b4-2c1c0111c0e4">
				<ee:message>
				</ee:message>
				<ee:variables>
						<ee:set-variable resource="dwl/outbound-poAck-processing-subflow/v_httpOperationPostAPM.dwl" variableName="httpOperation" />
				</ee:variables>
			</ee:transform>
				<logger level="DEBUG" doc:name="Log DEBUG: APM Request" doc:id="18cffda4-7a1c-4b08-8016-ccd251a4330e" message="#[%dw 2.0&#10;output application/json&#10;---&#10;{&#10;	event: &quot;APM flow start&quot;,&#10;	flow: flow.name,&#10;	application: app.name,&#10;	environment: Mule::p('mule.env'),&#10;	timestamp: now(),&#10;	correlationId: vars.initialVariables.correlationId&#10;}]" category="${logger.debug.category}" />
				<flow-ref doc:name="Flow Reference To commom-http-request-subflow" doc:id="acbd8490-85ef-4ac4-a32a-dbfa06612a04" name="common-http-request-subflow" target="transmissionId" targetValue="#[attributes.headers.'x-apm-trx-id']" />
				<logger level="DEBUG" doc:name="LOG DEBUG: APM Response" doc:id="5de34d2b-0454-4b0c-8f01-f79ac4b90f7e" message="#[%dw 2.0&#10;output application/json&#10;---&#10;{&#10;	event: &quot;APM flow ended&quot;,&#10;	flow: flow.name,&#10;	application: app.name,&#10;	environment: Mule::p('mule.env'),&#10;	timestamp: now(),&#10;	correlationId: vars.initialVariables.correlationId,&#10;	transmissionId: vars.transmissionId&#10;}]" category="${logger.debug.category}" />
				<ee:transform doc:name="Transaction api payload  transformation" doc:id="98aac730-ba0e-47ca-bdc2-a24bee804a39">
				<ee:message>
						<ee:set-payload resource="dwl/outbound-poAck-processing-subflow/p_accumulatedSuccessResponse.dwl" />
				</ee:message>
			</ee:transform>
				<error-handler >
					<on-error-continue enableNotifications="true" logException="true" doc:name="On Error Continue" doc:id="14fb75ef-39d7-4081-b02f-4760284bdc43" >
						<ee:transform doc:name="var : httpStatus" doc:id="dcd9c726-ffd1-47f9-8df9-7695adf57dde" >
							<ee:message />
							<ee:variables >
								<ee:set-variable variableName="httpStatus" ><![CDATA[%dw 2.0
output application/json
---
if((error.errorType.namespace ++ ":" ++ error.errorType.identifier) == "APIKIT:BAD_REQUEST") (400) else
if((error.errorType.namespace ++ ":" ++ error.errorType.identifier) == "APIKIT:NOT_FOUND") (404) else
if((error.errorType.namespace ++ ":" ++ error.errorType.identifier) == "APIKIT:METHOD_NOT_ALLOWED") (405) else
if((error.errorType.namespace ++ ":" ++ error.errorType.identifier) == "APIKIT:NOT_ACCEPTABLE") (406) else
if((error.errorType.namespace ++ ":" ++ error.errorType.identifier) == "APIKIT:UNSUPPORTED_MEDIA_TYPE") (415) else (500)]]></ee:set-variable>
							</ee:variables>
						</ee:transform>
						<ee:transform doc:name="Preparing error payload for transaction api" doc:id="155f39e3-e1f8-454d-adc3-ffb7efe6bbec" >
							<ee:message >
								<ee:set-payload resource="dwl/outbound-poAck-processing-subflow/p_accumulatedFailedResponse.dwl" />
							</ee:message>
						</ee:transform>
						<logger level="INFO" doc:name="LOG INFO : Error" doc:id="81e2ea04-822d-4887-a3b3-1c526cb37588" message='#[%dw 2.0&#10;output application/json&#10;---&#10;{&#10;	event: "Errored PO",&#10;	flow: flow.name,&#10;	application: app.name,&#10;	timestamp: now(),&#10;	correlationId: vars.initialVariables.correlationId,&#10;	poSummary: payload&#10;}]' />
					</on-error-continue>
				</error-handler>
			</try>
		</parallel-foreach>
		<logger level="DEBUG" doc:name="LOG DEBUG:  PO Status" doc:id="8a8997c8-0ba7-49ee-a18b-5e0200d6cabe" message='#[%dw 2.0&#10;output application/json&#10;---&#10;{&#10;	event: "Parllel for each process completed",&#10;	flow: flow.name,&#10;	application: app.name,&#10;	timestamp: now(),&#10;	correlationId: vars.initialVariables.correlationId,&#10;	poSummary: payload&#10;}]' category="${logger.debug.category}" />
		<ee:transform doc:name="Prepare payload for transaction API" doc:id="0aa35ffe-5022-46b1-85c7-8017db210feb" >
			<ee:message >
			</ee:message>
			<ee:variables >
				<ee:set-variable resource="dwl/outbound-poAck-processing-subflow/v_erroredPOs.dwl" variableName="erroredPOs" />
				<ee:set-variable resource="dwl/outbound-poAck-processing-subflow/v_parllelForEachResponse.dwl" variableName="parllelForEachResponse" />
				<ee:set-variable resource="dwl/outbound-poAck-processing-subflow/v_transactionRequestPayload.dwl" variableName="transactionRequestPayload" />
			</ee:variables>
		</ee:transform>
		<ee:transform doc:name="var: httpOperation-post Transaction api, vendorName" doc:id="a9fe6ca4-482e-4ff9-94d3-4d625b9dc3da" >
			<ee:message >
			</ee:message>
			<ee:variables >
				<ee:set-variable variableName="vendorName" ><![CDATA[%dw 2.0
output application/json
---
if (!isEmpty(payload.payload.partnerId))
(payload.payload.partnerId map  Mule::p("partner.outbound." ++ $)) distinctBy $
else null
]]></ee:set-variable>
				<ee:set-variable resource="dwl/outbound-poAck-processing-subflow/v_httpOperationFlagUpdate.dwl" variableName="httpOperation" />
			</ee:variables>
		</ee:transform>
		<try doc:name="Try" doc:id="b5cf7477-8061-4f87-a9cb-ce5c6aed0df9" >
			<flow-ref doc:name="Flow Reference To commom-http-request-subflow" doc:id="b3a959fd-f2fc-4a61-ac48-7a5ca76fe311" name="common-http-request-subflow" />
			<choice doc:name="is Flag Updation Successful?" doc:id="34954d9e-45dc-4d64-acae-51eaafb6fb09" >
				<when expression='#[payload.TransactionSetResult.Summary.Failed != "0"]' >
					<raise-error doc:name="CUSTOM:P21_FAILED" doc:id="fc641a5c-207d-4f97-8645-68e142722838" type="CUSTOM:P21_FAILED" description='#[payload.Messages joinBy ","]' />
				</when>
				<otherwise >
					<logger level="DEBUG" doc:name="LOG INFO : Flag Updated" doc:id="daf4d61f-1e45-45bd-a780-7aecbc7082e0" message='#[%dw 2.0&#10;output application/json&#10;var t = payload.TransactionSetResult.Results.Transactions.*Transaction---&#10;{&#10;	event: "Flag updation was Successful in P21",&#10;	application: app.name,&#10;	timestamp: now(),&#10;	correlationId: vars.initialVariables.correlationId,&#10;    successFlagPO: &#10;		t filter ($.Status == "Passed") &#10;		  map $.DataElements.DataElement.Rows.Row.Edits.Edit.Value,&#10;}]' />
				</otherwise>
			</choice>
			<error-handler >
				<on-error-continue enableNotifications="true" logException="true" doc:name="On Error Continue" doc:id="b1c404ef-0514-4a75-b606-5e25f46d1977" >
					<choice doc:name="Choice for Error Type " doc:id="61553d76-e7f9-43e2-8772-1b013bf2fc3c" >
						<when expression='#[output json --- error.errorType.identifier == "RETRY_EXHAUSTED"]' >
							<ee:transform doc:name="Preparing Email Template for P21 connectivity issues, var : subject" doc:id="48d91936-8dfa-4b74-84ca-2b84337b8e0f" >
								<ee:message >
									<ee:set-payload resource="dwl/outbound-poAck-processing-subflow/p_connectivityError.dwl" />
								</ee:message>
								<ee:variables >
									<ee:set-variable resource="dwl/outbound-poAck-processing-subflow/v_connectivityErrorSubject.dwl" variableName="subject" />
								</ee:variables>
							</ee:transform>
							<logger level="INFO" doc:name="Log INFO : Error" doc:id="e59582aa-43e0-48d8-914d-738433542e0e" message='#[%dw 2.0&#10;output application/json&#10;---&#10;{&#10;	event: "Connectivity Error in P21",&#10;	error: error.errorType.identifier,&#10;	flow: flow.name,&#10;	application: app.name,&#10;	timestamp: now(),&#10;	correlationId: vars.initialVariables.correlationId&#10;}]' />
							<flow-ref doc:name="Flow Reference to send-email-subflow" doc:id="fb44fd0f-db1d-4ce8-8393-e9387a3c62e8" name="send-email-subflow" />
						</when>
						<otherwise >
							<ee:transform doc:name="Prepare Error response for p21 flag updation issues, var : subject" doc:id="2d3f2532-3ae6-44e7-9310-035bf68f1b6e" >
								<ee:message >
									<ee:set-payload resource="dwl/outbound-poAck-processing-subflow/p_flagUpdationError.dwl" />
								</ee:message>
								<ee:variables />
							</ee:transform>
							<ee:transform doc:name="Prepare Template Email, var : subject" doc:id="1ff02cdf-e3ac-4779-aa59-bcb6a38e2ae9" >
								<ee:message >
									<ee:set-payload resource="dwl/outbound-poAck-processing-subflow/p_flagUpdationErrorTemplate.dwl" />
								</ee:message>
								<ee:variables >
									<ee:set-variable resource="dwl/outbound-poAck-processing-subflow/v_flagUpdationErrorSubject.dwl" variableName="subject" />
								</ee:variables>
							</ee:transform>
							<logger level="INFO" doc:name="Log INFO : Error" doc:id="bf953ca0-2645-4f3e-b44a-f5cddace4ffa" message='#[%dw 2.0&#10;output application/json&#10;---&#10;{&#10;	event: "Flag Updation Error in P21",&#10;	error: error.errorType.identifier,&#10;	flow: flow.name,&#10;	application: app.name,&#10;	timestamp: now(),&#10;	correlationId: vars.initialVariables.correlationId&#10;}]' />
							<flow-ref doc:name="Flow Reference to send-email-subflow" doc:id="72a497d7-f9ef-4c77-9082-ad9db86bd915" name="send-email-subflow" />
						</otherwise>
					</choice>
				</on-error-continue>
			</error-handler>
		</try>
		<foreach doc:name="For Each: Iteration Over Errored POs" doc:id="ad333071-ad43-4fb1-95e7-90c2bbe9aac7" collection="#[vars.erroredPOs]">
			<ee:transform doc:name="Preparing Email Template, var : subject" doc:id="d1ce1bc7-f535-4fa4-afb7-0928ae701184">
				<ee:message>
					<ee:set-payload resource="dwl/outbound-poAck-processing-subflow/p_validationError.dwl" />
				</ee:message>
				<ee:variables>
					<ee:set-variable resource="dwl/outbound-poAck-processing-subflow/v_validationErrorSubject.dwl" variableName="subject" />
				</ee:variables>
			</ee:transform>
			<flow-ref doc:name="send-email-subflow" doc:id="1a71241c-8444-4d2a-8396-bfd66005cc4e" name="send-email-subflow" />
		</foreach>
		<logger level="INFO" doc:name="LOG INFO : END" doc:id="7030904c-c1ba-4779-96cd-233691716bdb" message="#[%dw 2.0&#10;output application/json&#10;---&#10;{&#10;	event: &quot;END&quot;,&#10;	flow: flow.name,&#10;	application: app.name,&#10;	environment: p('mule.env'),&#10;	timestamp: now(),&#10;	correlationId: vars.initialVariables.correlationId,&#10;	sourceSystem: &quot;P21&quot;,&#10;	targetSystem: &quot;APM - Anypoint Partner Manager&quot;&#10;}]" />
	</sub-flow>
</mule>
